mrmd_orchestrator/__init__.py
mrmd_orchestrator/cli.py
mrmd_orchestrator/config.py
mrmd_orchestrator/orchestrator.py
mrmd_orchestrator/processes.py
mrmd_orchestrator/server.py
mrmd_orchestrator-0.1.1.dist-info/METADATA
mrmd_orchestrator-0.1.1.dist-info/WHEEL
mrmd_orchestrator-0.1.1.dist-info/entry_points.txt
mrmd_orchestrator-0.1.1.dist-info/RECORD
