Metadata-Version: 2.4
Name: mrmd-orchestrator
Version: 0.1.1
Summary: Orchestrator for mrmd services - starts sync, monitors, and runtimes
Author: Maxime
License-Expression: MIT
Requires-Python: >=3.10
Requires-Dist: fastapi>=0.104.0
Requires-Dist: httpx>=0.25.0
Requires-Dist: uvicorn[standard]>=0.24.0
Provides-Extra: dev
Requires-Dist: pytest-asyncio>=0.21.0; extra == 'dev'
Requires-Dist: pytest>=7.0.0; extra == 'dev'
